atacs/__init__.py
atacs/macd.py
atacs/rsi.py
atacs/stats.py
ATACS-0.1.5.dist-info/LICENSE
ATACS-0.1.5.dist-info/METADATA
ATACS-0.1.5.dist-info/WHEEL
ATACS-0.1.5.dist-info/top_level.txt
ATACS-0.1.5.dist-info/RECORD
